app/__init__.py
app/app.py
app/index.py
app/temp/dashboard-2.py
app/util/parsing.py
app/views/__init__.py
app/views/dashboard1.py
app/views/dashboard2.py
app/views/dashboard3.py
common/__init__.py
common/band_filter.py
common/generate_template.py
common/power_spectrum.py
common/rpeak_detection.py
common/utils.py
data/__init__.py
data/signal_io.py
data/signal_sqi_class.py
dataset/__init__.py
dataset/example_data.py
pipeline/__init__.py
pipeline/pipeline_functions.py
pipeline/pipeline_highlevel.py
preprocess/__init__.py
preprocess/preprocess_signal.py
preprocess/removal_utilities.py
preprocess/segment_split.py
resource/__init__.py
resource/citations.bib
resource/peak_dectector_list.txt
resource/rule_dict.json
resource/sqi_dict.json
rule/__init__.py
rule/rule_class.py
rule/ruleset_class.py
sqi/__init__.py
sqi/dtw_sqi.py
sqi/hrv_sqi.py
sqi/rpeaks_sqi.py
sqi/standard_sqi.py
sqi/waveform_sqi.py
vital_sqi/__init__.py
vital_sqi/app/__init__.py
vital_sqi/app/app.py
vital_sqi/app/index.py
vital_sqi/app/temp/dashboard-2.py
vital_sqi/app/util/parsing.py
vital_sqi/app/views/__init__.py
vital_sqi/app/views/dashboard1.py
vital_sqi/app/views/dashboard2.py
vital_sqi/app/views/dashboard3.py
vital_sqi/common/__init__.py
vital_sqi/common/band_filter.py
vital_sqi/common/generate_template.py
vital_sqi/common/power_spectrum.py
vital_sqi/common/rpeak_detection.py
vital_sqi/common/utils.py
vital_sqi/data/__init__.py
vital_sqi/data/signal_io.py
vital_sqi/data/signal_sqi_class.py
vital_sqi/dataset/__init__.py
vital_sqi/dataset/example_data.py
vital_sqi/pipeline/__init__.py
vital_sqi/pipeline/pipeline_functions.py
vital_sqi/pipeline/pipeline_highlevel.py
vital_sqi/preprocess/__init__.py
vital_sqi/preprocess/preprocess_signal.py
vital_sqi/preprocess/removal_utilities.py
vital_sqi/preprocess/segment_split.py
vital_sqi/resource/__init__.py
vital_sqi/resource/citations.bib
vital_sqi/resource/peak_dectector_list.txt
vital_sqi/resource/rule_dict.json
vital_sqi/resource/rule_dict_test.json
vitalsqi_toolkit-1.0.2.dist-info/LICENSE
vitalsqi_toolkit-1.0.2.dist-info/METADATA
vitalsqi_toolkit-1.0.2.dist-info/WHEEL
vitalsqi_toolkit-1.0.2.dist-info/top_level.txt
vitalsqi_toolkit-1.0.2.dist-info/RECORD
