Metadata-Version: 2.1
Name: vitalsqi-toolkit
Version: 1.0.2
Summary: A toolkit for signal quality analysis of ECG and PPG signals
Home-page: https://github.com/Oucru-Innovations/vital-sqi
Author: Khoa Le, Hai Ho, Stefan Karolcik, Heloise Greeff
Author-email: Khoa Le <khoaldv@oucru.org>, Hai Ho <haihb@oucru.org>, Stefan Karolcik <s.karolcik@imperial.ac.uk>, Heloise Greeff <heloise.greeff@eng.ox.ac.uk>
Maintainer: Hai Ho, Khoa Le
Maintainer-email: haihb@oucru.org, khoaldv@oucru.org
License: MIT
Project-URL: Documentation, https://pypi.org/project/vitalsqi_toolkit/
Project-URL: Source, https://github.com/Oucru-Innovations/vital-sqi
Project-URL: Tracker, https://github.com/Oucru-Innovations/vital-sqi/issues
Project-URL: Homepage, https://github.com/Oucru-Innovations/vital-sqi
Keywords: signal quality,ECG,PPG,toolkit
Classifier: Development Status :: 4 - Beta
Classifier: Programming Language :: Python :: 3
Classifier: Programming Language :: Python :: 3.7
Classifier: Programming Language :: Python :: 3.8
Classifier: Programming Language :: Python :: 3.9
Classifier: Programming Language :: Python :: 3.11
Classifier: License :: OSI Approved :: MIT License
Classifier: Operating System :: OS Independent
Requires-Python: >=3.7
License-File: LICENSE
Requires-Dist: vitalDSP
Requires-Dist: openpyxl
Requires-Dist: pmdarima (>=1.8.0)
Requires-Dist: matplotlib
Requires-Dist: numpy (>=1.20.2)
Requires-Dist: pandas (>=1.1.5)
Requires-Dist: plotly (>=4.14.3)
Requires-Dist: scikit-learn (>=0.24.1)
Requires-Dist: scipy (>=1.6.0)
Requires-Dist: statsmodels (>=0.12.1)
Requires-Dist: tqdm (>=4.56.0)
Requires-Dist: pyEDFlib (>=0.1.20)
Requires-Dist: pycwt (>=0.3.0a22)
Requires-Dist: wfdb (>=3.3.0)
Requires-Dist: datetimerange (>=1.0.0)
Requires-Dist: dateparser (>=1.0.0)
Requires-Dist: pyflowchart (>=0.1.3)
Provides-Extra: testing
Requires-Dist: pytest ; extra == 'testing'
Requires-Dist: pytest-cov ; extra == 'testing'
Requires-Dist: pytest-mock ; extra == 'testing'
Requires-Dist: tox ; extra == 'testing'
Requires-Dist: dash[testing] ; extra == 'testing'
Requires-Dist: webdriver-manager ; extra == 'testing'
Requires-Dist: selenium ; extra == 'testing'
